text_emotion/__init__.py
text_emotion/emotion.py
text_emotion-0.0.3.dist-info/LICENSE
text_emotion-0.0.3.dist-info/METADATA
text_emotion-0.0.3.dist-info/WHEEL
text_emotion-0.0.3.dist-info/RECORD
