Metadata-Version: 2.1
Name: text-emotion
Version: 0.0.3
Summary: Multilingual Emotion Classification
Home-page: https://github.com/ma2za/text-emotion
License: MIT
Keywords: text-emotion,xlm-roberta,text-classification,multilingual
Author: ma2za
Author-email: mazzapaolo2019@gmail.com
Requires-Python: >=3.8,<4.0
Classifier: License :: OSI Approved :: MIT License
Classifier: Programming Language :: Python :: 3
Classifier: Programming Language :: Python :: 3.8
Classifier: Programming Language :: Python :: 3.9
Classifier: Programming Language :: Python :: 3.10
Classifier: Programming Language :: Python :: 3.11
Provides-Extra: translate
Requires-Dist: easynmt (>=2.0.2,<3.0.0) ; extra == "translate"
Requires-Dist: fasttext (>=0.9.2,<0.10.0) ; extra == "translate"
Requires-Dist: requests (>=2.31.0,<3.0.0) ; extra == "translate"
Requires-Dist: torch (>=2.0.1,<3.0.0)
Requires-Dist: transformers (>=4.30.1,<5.0.0)
Project-URL: Repository, https://github.com/ma2za/text-emotion
